hygroup/__init__.py
hygroup/channel.py
hygroup/session.py
hygroup/utils.py
hygroup/agent/__init__.py
hygroup/agent/base.py
hygroup/agent/utils.py
hygroup/connect/__init__.py
hygroup/connect/composio.py
hygroup/connect/notion.py
hygroup/connect/toolkits.json
hygroup/connect/utils.py
hygroup/factory/__init__.py
hygroup/factory/example.py
hygroup/factory/prompts/__init__.py
hygroup/factory/prompts/office.md
hygroup/factory/prompts/reasoner.md
hygroup/factory/prompts/system/__init__.py
hygroup/factory/prompts/system/prompt.md
hygroup/factory/prompts/system/prompt.py
hygroup/factory/tools/__init__.py
hygroup/factory/tools/weather.py
hygroup/gateway/__init__.py
hygroup/gateway/base.py
hygroup/gateway/terminal.py
hygroup/gateway/github/__init__.py
hygroup/gateway/github/events.py
hygroup/gateway/github/gateway.py
hygroup/gateway/github/service.py
hygroup/gateway/github/webhook/__init__.py
hygroup/gateway/github/webhook/api.py
hygroup/gateway/github/webhook/app.py
hygroup/gateway/github/webhook/config.py
hygroup/gateway/github/webhook/dependencies.py
hygroup/gateway/github/webhook/logging.yaml
hygroup/gateway/slack/__init__.py
hygroup/gateway/slack/commands.py
hygroup/gateway/slack/context.py
hygroup/gateway/slack/gateway.py
hygroup/gateway/slack/permissions.py
hygroup/gateway/slack/responses.py
hygroup/gateway/slack/thread.py
hygroup/gateway/slack/utils.py
hygroup/gateway/slack/app_home/__init__.py
hygroup/gateway/slack/app_home/handlers.py
hygroup/gateway/slack/app_home/views.py
hygroup/gateway/slack/app_home/preferences/__init__.py
hygroup/gateway/slack/app_home/preferences/handlers.py
hygroup/gateway/slack/app_home/preferences/views.py
hygroup/gateway/slack/app_home/secrets/__init__.py
hygroup/gateway/slack/app_home/secrets/handlers.py
hygroup/gateway/slack/app_home/secrets/views.py
hygroup/scripts/__init__.py
hygroup/scripts/composio.py
hygroup/scripts/notion.py
hygroup/scripts/server.py
hygroup/scripts/terminal/__init__.py
hygroup/scripts/terminal/channel.py
hybrid_groups-0.2.1.dist-info/METADATA
hybrid_groups-0.2.1.dist-info/WHEEL
hybrid_groups-0.2.1.dist-info/licenses/LICENSE
hybrid_groups-0.2.1.dist-info/RECORD
