Metadata-Version: 2.4
Name: hybrid-groups
Version: 0.2.1
Summary: A multi-user, multi-agent collaboration platform
Author-email: Martin Krasser <martin@gradion.ai>, Christoph Stumpf <chris@gradion.ai>
License-Expression: Apache-2.0
License-File: LICENSE
Requires-Python: <3.14,>=3.11
Requires-Dist: aioconsole<0.9,>=0.8.1
Requires-Dist: aiodocker<0.25,>=0.24.0
Requires-Dist: aiofiles<25,>=24.1.0
Requires-Dist: aiohttp<4,>=3.11.16
Requires-Dist: bcrypt<5,>=4.3.0
Requires-Dist: composio-client>=1.7.0
Requires-Dist: cryptography<46,>=45.0.3
Requires-Dist: datasets<4,>=3.6.0
Requires-Dist: fastapi[all]<0.116,>=0.115.12
Requires-Dist: gitingest<0.2,>=0.1.4
Requires-Dist: google-genai<2,>=1.21.1
Requires-Dist: group-genie<0.1,>=0.0.2
Requires-Dist: markdown-to-mrkdwn<0.3,>=0.2.0
Requires-Dist: mcp<2,>=1.13.0
Requires-Dist: pillow<12,>=11.3.0
Requires-Dist: pygithub<3,>=2.6.1
Requires-Dist: rich<15,>=14.0.0
Requires-Dist: slack-bolt<2,>=1.23.0
